aws_plugin_bucket_policy/__init__.py
aws_plugin_bucket_policy/bp_classes.py
aws_plugin_bucket_policy/bucket_policy.py
aws_plugin_bucket_policy/constants.py
aws_plugin_bucket_policy/utils.py
aws_plugin_bucket_policy-1.0.1.dist-info/LICENSE
aws_plugin_bucket_policy-1.0.1.dist-info/METADATA
aws_plugin_bucket_policy-1.0.1.dist-info/WHEEL
aws_plugin_bucket_policy-1.0.1.dist-info/RECORD
