Metadata-Version: 2.1
Name: aws-plugin-bucket-policy
Version: 1.0.1
Summary: awscli S3 bucket-policy plugin
Author: Tomas Hlava
Author-email: hlava@cesnet.cz
Requires-Python: >=3.8,<4.0
Classifier: Programming Language :: Python :: 3
Classifier: Programming Language :: Python :: 3.8
Classifier: Programming Language :: Python :: 3.9
Classifier: Programming Language :: Python :: 3.10
Classifier: Programming Language :: Python :: 3.11
Requires-Dist: awscli (>=1.29,<2.0)
